nonebot_reply/__init__.py
nonebot_reply/config.py
nonebot_reply-1.4.dist-info/LICENSE
nonebot_reply-1.4.dist-info/METADATA
nonebot_reply-1.4.dist-info/WHEEL
nonebot_reply-1.4.dist-info/top_level.txt
nonebot_reply-1.4.dist-info/RECORD
