Metadata-Version: 2.1
Name: nonebot_reply
Version: 1.4
Summary: A small example package
Home-page: https://github.com/hriyel/nonebot_reply.git
Author: hriyel
Author-email: hriyel <1249781871@qq.com>
Project-URL: Homepage, https://github.com/hriyel/nonebot_reply.git
Classifier: Programming Language :: Python :: 3
Classifier: License :: OSI Approved :: MIT License
Classifier: Operating System :: OS Independent
Requires-Python: >=3.8
License-File: LICENSE
